{"head":{"title":"Donating","hero":"https://farm5.staticflickr.com/4042/5077124966_cb0bd93939_o_d.jpg","description":"Donating We accept donations during operating hours at the Friends of the Library, or donations can be made to the library at other times.…"},"body":"<h2 id=\"donating\"><a href=\"#donating\" class=\"phenomic-HeadingAnchor\">#</a>Donating</h2>\n<p>We accept donations during operating hours at the Friends of the Library, or\ndonations can be made to the library at other times. We accept everything\nexcept magazines and encyclopedias. If you wish to donate money, please fill\nout a monetary donation form. You can pick up a form at the bookstore or\ndownload one <a href=\"/assets/donation_form.pdf\">here</a>.</p>\n","__filename":"donating.md","__url":"/donating/","__resourceUrl":"/donating/index.html","__dataUrl":"/donating/index.html.264cab15432235cd5c96d87448c2acc1.json"}